{"type": "Feature", "id": 12524539, "properties": {"woe:id": 12524539, "woe:parent_id": 377249, "woe:name": "Ladouanie Airport", "woe:placetype": 14, "woe:placetype_name": "Airport", "woe:lang": "ENG", "iso:country": "SR", "meta:provider": ["geoplanet:7.3.1", "geoplanet:7.3.2", "geoplanet:7.4.0", "geoplanet:7.4.1", "geoplanet:7.5.1", "geoplanet:7.5.2", "geoplanet:7.6.0", "geoplanet:7.8.1", "geoplanet:7.9.0", "geoplanet:7.10.0", "geoplanet:8.0.0", "woeplanet:8.0.0"], "meta:indexed": "2020-08-20T20:57:43.220064", "woe:alias_ENG_V": ["LDO Airport", "LDO", "Ladouanie"], "meta:updated": "2020-08-22T02:29:00.108807", "woe:hierarchy": {"continent": 24865673, "country": 23424913, "town": 0, "planet": 1, "county": 0, "suburb": 0, "state": 2346414, "region": 0, "localadmin": 0}, "woe:timezone_id": 28350783, "woe:hash": "dbb8fvyy9rgj", "woe:centroid": [-55.416698, 4.38333], "geom:latitude": 4.38333, "geom:longitude": -55.416698, "geom:hash": "dbb8fvyy9rgj", "woe:latitude": 4.38333, "geom:centroid": [-55.416698, 4.38333], "woe:longitude": -55.416698, "woe:repo": "woeplanet-airport-sr"}, "geometry": {"coordinates": [-55.416698, 4.38333], "type": "Point"}}